microstatistics/__init__.py
microstatistics/command_line.py
microstatistics/diversities.py
microstatistics/diversities_test.py
microstatistics/graphing_functions.py
microstatistics/gui_licence.py
microstatistics/gui_manual.py
microstatistics/gui_microstatistics.py
microstatistics-0.5.5.dist-info/LICENSE
microstatistics-0.5.5.dist-info/LICENSE.md
microstatistics-0.5.5.dist-info/METADATA
microstatistics-0.5.5.dist-info/WHEEL
microstatistics-0.5.5.dist-info/entry_points.txt
microstatistics-0.5.5.dist-info/top_level.txt
microstatistics-0.5.5.dist-info/RECORD
