Metadata-Version: 2.1
Name: microstatistics
Version: 0.5.5
Summary: A package for micropalaeontological statisics with a Qt5 gui. Launched with microstatistics-start. Requires installation through pip3.
Home-page: https://github.com/GeluOltean/microstatistics
Author: Gelu Oltean
Author-email: geluoltean8@gmail.com
License: GNU GPL 3
Platform: UNKNOWN
Classifier: Development Status :: 3 - Alpha
Classifier: Environment :: X11 Applications :: Qt
Classifier: Environment :: Console
Classifier: Operating System :: OS Independent
Classifier: Intended Audience :: Science/Research
Classifier: License :: OSI Approved :: GNU General Public License v3 (GPLv3)
Classifier: Programming Language :: Python :: 3.6
Requires-Dist: PyQt5
Requires-Dist: matplotlib
Requires-Dist: numpy
Requires-Dist: pandas
Requires-Dist: scipy
Requires-Dist: sklearn
Requires-Dist: xlrd
